SATK/__init__.py
SATK/module.py
SATK/ABSA/__init__.py
SATK/ABSA/api.py
SATK/classifier/__init__.py
SATK/classifier/call_test.py
SATK/classifier/pipelines.py
absa/__init__.py
absa/module.py
absa/absa/__init__.py
absa/absa/api.py
absa/absa/utils/__init__.py
absa/absa/utils/span.py
absa/classifier/__init__.py
absa/classifier/call_test.py
absa/classifier/pipelines.py
absa-0.0.0.0.dist-info/LICENSE
absa-0.0.0.0.dist-info/METADATA
absa-0.0.0.0.dist-info/WHEEL
absa-0.0.0.0.dist-info/top_level.txt
absa-0.0.0.0.dist-info/RECORD
